merger_defines.v
// 
// Author: Andrew Feldman (afeld2012@gmail.com)
//
// Copyright (c) 2019 Andrew Feldman and MIT EEMS laboratory.
//
// Permission is hereby granted, free of charge, to any person obtaining a copy of this software and associated
// documentation files (the "Software"), to deal in the Software without restriction, including without limitation the
// rights to use, copy, modify, merge, publish, distribute, sublicense, and/or sell copies of the Software, and to
// permit persons to whom the Software is furnished to do so, subject to the following conditions:
//
// The above copyright notice and this permission notice shall be included in all copies or substantial portions of the
// Software.
//
// THE SOFTWARE IS PROVIDED "AS IS", WITHOUT WARRANTY OF ANY KIND, EXPRESS OR IMPLIED, INCLUDING BUT NOT LIMITED TO THE
// WARRANTIES OF MERCHANTABILITY, FITNESS FOR A PARTICULAR PURPOSE AND NONINFRINGEMENT. IN NO EVENT SHALL THE AUTHORS OR
// COPYRIGHT HOLDERS BE LIABLE FOR ANY CLAIM, DAMAGES OR OTHER LIABILITY, WHETHER IN AN ACTION OF CONTRACT, TORT OR
// OTHERWISE, ARISING FROM, OUT OF OR IN CONNECTION WITH THE SOFTWARE OR THE USE OR OTHER DEALINGS IN THE SOFTWARE.

/*
*  Parameterize mergers.
*/

`define COORD_BITS 32
`define RADIX 2

dut/binary_merger.v
// binary_merger.v
// Author: Andrew Feldman, 11/10/2021
//
// Parameterized binary merger component

module binary_merger 
              #(parameter MERGER_COORD_BITS = 32)
              (
              input wire clock,
              input wire reset,
              input wire [(2*MERGER_COORD_BITS-1):0] coord_in,
              output wire [(MERGER_COORD_BITS-1):0] coord,
              input wire selected,
              output wire [1:0] fetch_next
);
    
    wire comparison;
    wire [(MERGER_COORD_BITS-1):0] coord_0;
    wire [(MERGER_COORD_BITS-1):0] coord_1;

    // Breakout separate coordinates from input net
    assign coord_0 = coord_in[(MERGER_COORD_BITS-1):0];
    assign coord_1 = coord_in[(2*MERGER_COORD_BITS-1):MERGER_COORD_BITS];
    assign fetch_next = {fetch_next_from_1,fetch_next_from_0};

    // Merge
    assign comparison = (coord_0 < coord_1);
    assign coord = comparison ? coord_0 : coord_1;
    assign fetch_next_from_0 = comparison & selected;
    assign fetch_next_from_1 = (~comparison) & selected;

endmodule

dut/merger.v
// merger.v
// Author: Andrew Feldman, 11/10/2021
//
// Top-level merger component with registered output

module merger
              #(parameter MERGER_COORD_BITS = 32,
                parameter MERGER_RADIX = 2  
              )
              (input wire clock,
              input wire reset,
              input wire [(MERGER_RADIX*MERGER_COORD_BITS-1):0] coord_in,
              output reg [(MERGER_COORD_BITS-1):0] coord,
              input wire selected,
              output reg [(MERGER_RADIX-1):0]  fetch_next
);

    // Will plug into the outputs of a combinational merger
    wire [(MERGER_COORD_BITS-1):0] coord_wire;
    wire [(MERGER_RADIX-1):0] fetch_next_wire;

    // Characterize the tree of binary mergers comprising this radix-R merger
    // Number of binary merger tree nodes:
    localparam BINARY_MERGER_COUNT = MERGER_RADIX - 1; 
    // Number of fetch/select signals between binary mergers
    localparam FETCH_WIRE_COUNT = BINARY_MERGER_COUNT + MERGER_RADIX; 
    // Aggregate size of nets carrying coordinates between binary merge units
    localparam COORD_WIRE_COUNT = MERGER_COORD_BITS * FETCH_WIRE_COUNT; 
    // Pointers to where the coord_in input net "hooks in" to the tree of coordinate nets
    localparam LEAF_END_IDX = FETCH_WIRE_COUNT - 1;
    localparam LEAF_START_IDX = LEAF_END_IDX - MERGER_RADIX + 1;
    
    // Flattened tree structures for fetch/select wires and coordinate nets between binary mergers
    wire [(FETCH_WIRE_COUNT-1):0] fetch_wires;
    wire [(COORD_WIRE_COUNT-1):0] coord_wires;

    // Create the tree of binary mergers based on the localparams above
    generate
        genvar node_idx;
        for (node_idx = 0; node_idx < BINARY_MERGER_COUNT; node_idx = node_idx + 1) begin
            binary_merger merger_tree_node (
                .clock(clock),
                .reset(reset),
                .coord_in(coord_wires[((node_idx*2 + 3)*MERGER_COORD_BITS - 1):((node_idx*2 + 1)*MERGER_COORD_BITS)]),
                .coord(coord_wires[((node_idx + 1)*MERGER_COORD_BITS - 1):(node_idx*MERGER_COORD_BITS)]),
                .selected(fetch_wires[node_idx]),
                .fetch_next(fetch_wires[(node_idx*2 + 2):(node_idx*2 + 1)]) // (node_idx*2 + 2):(node_idx*2 + 1)
            );
            
            defparam merger_tree_node.MERGER_COORD_BITS = MERGER_COORD_BITS;
            
        end
    endgenerate
    
    // Hook the tree of coordinate nets up to the
    // top-level input wires
    assign coord_wires[(MERGER_COORD_BITS*FETCH_WIRE_COUNT - 1):(MERGER_COORD_BITS*LEAF_START_IDX)] = coord_in;
    assign fetch_wires[0] = selected;

    // Final layer of sequential logic -
    // hook the tree of coordinate nets & fetch/select wires
    // up to the top-level output registers
    always @(posedge clock) begin
        if (reset) begin
            coord <= 0;
            fetch_next <= 0;
        end else if (clock) begin
            coord <= coord_wires[(MERGER_COORD_BITS - 1):0];
            fetch_next <= fetch_wires[LEAF_END_IDX:LEAF_START_IDX]; // LEAF_END_IDX:LEAF_START_IDX
        end
    end

endmodule

testbench/tb_parameterized_merger.v
// tb_parameterized_merger.v
// Author: Andrew Feldman 11/10/2021
//
// Testbench for parameterized merger component

`timescale 1ns/1ps
`include "merger_defines.v"

module tb_parameterized_merger;

    // Track wire inputs and register outputs from merger
    reg clk;
    reg rst;
    reg [(`COORD_BITS-1):0] c0;
    reg [(`COORD_BITS-1):0] c1;
    reg [(`COORD_BITS-1):0] c2;    
    reg [(`COORD_BITS-1):0] c3;    
    wire [(`COORD_BITS-1):0] c;
    reg sel;
    wire f0;
    wire f1;
    wire f2;
    wire f3;    

    // Instantiate merger, parameterized by radix & coordinate bits
    merger dut (
        .clock(clk),
        .reset(rst),
//        .coord_in({c3,c2,c1,c0}),
        .coord_in({c1,c0}),
        .coord(c),
        .selected(sel),
//        .fetch_next({f3,f2,f1,f0})   
        .fetch_next({f1,f0})      
    );    

    defparam dut.MERGER_RADIX = `RADIX;
    defparam dut.MERGER_COORD_BITS = `COORD_BITS;

    // Clock
    always begin
        #5;
        clk = !clk;
    end

    initial begin
        $dumpfile("merger.vcd");
        $dumpvars(0,tb_parameterized_merger);       
        // Initial condition
        clk=0;
        rst=1;
        sel=1;
        #100

        // Test: second coordinate is least
        rst=0;
        c0=8'd3;
        c1=8'd2;
        c2=8'd4;
        c3=8'd5;                        
        #100

        // Test: deselect while second coordinate is least
        sel=0;
        #100

        // Test: first coordinate is least 
        sel=1;
        c0=8'd2;
        c1=8'd3;
        c2=8'd4;
        c3=8'd5;                                
        #100

        // Test: deselect while first coordinate is least
        sel=0;
        #100

        // Test: third coordinate is least 
        sel=1;
        c0=8'd4;
        c1=8'd3;
        c2=8'd2;
        c3=8'd5;                                
        #100

        // Test: deselect while first coordinate is least
        sel=0;
        #100

        // Test: fourth coordinate is least 
        sel=1;
        c0=8'd4;
        c1=8'd3;
        c2=8'd5;
        c3=8'd2;                                
        #100

        // Test: deselect while first coordinate is least
        sel=0;
        #100


        $dumpoff;
        $finish;
    end

endmodule

dump.vcd
$date
	Wed Nov 10 20:06:45 2021
$end
$version
	Icarus Verilog
$end
$timescale
	1ps
$end
$scope module tb_parameterized_merger $end
$scope module dut $end
$scope begin genblk1[0] $end
$scope module merger_tree_node $end
$var wire 1 ! clock $end
$var wire 64 " coord_in [63:0] $end
$var wire 2 # fetch_next [1:0] $end
$var wire 1 $ fetch_next_from_0 $end
$var wire 1 % fetch_next_from_1 $end
$var wire 1 & reset $end
$var wire 1 ' selected $end
$var wire 32 ( coord_1 [31:0] $end
$var wire 32 ) coord_0 [31:0] $end
$var wire 32 * coord [31:0] $end
$var wire 1 + comparison $end
$upscope $end
$upscope $end
$upscope $end
$upscope $end
$scope module tb_parameterized_merger $end
$var wire 1 , f1 $end
$var wire 1 - f0 $end
$var wire 32 . c [31:0] $end
$var reg 32 / c0 [31:0] $end
$var reg 32 0 c1 [31:0] $end
$var reg 32 1 c2 [31:0] $end
$var reg 32 2 c3 [31:0] $end
$var reg 1 ! clk $end
$var reg 1 & rst $end
$var reg 1 3 sel $end
$scope module dut $end
$var wire 1 ! clock $end
$var wire 64 4 coord_in [63:0] $end
$var wire 1 & reset $end
$var wire 1 3 selected $end
$var wire 3 5 fetch_wires [2:0] $end
$var wire 96 6 coord_wires [95:0] $end
$var reg 32 7 coord [31:0] $end
$var reg 2 8 fetch_next [1:0] $end
$scope begin genblk1[0] $end
$scope module merger_tree_node $end
$upscope $end
$upscope $end
$upscope $end
$upscope $end
$enddefinitions $end
#0
$dumpvars
bx 8
bx 7
bx 6
bz1 5
bx 4
13
bx 2
bx 1
bx 0
bx /
bx .
x-
x,
x+
bx *
bx )
bx (
1'
1&
x%
x$
bz #
bx "
0!
$end
#5000
0-
0,
b0 8
b0 .
b0 7
1!
#10000
0!
#15000
1!
#20000
0!
#25000
1!
#30000
0!
#35000
1!
#40000
0!
#45000
1!
#50000
0!
#55000
1!
#60000
0!
#65000
1!
#70000
0!
#75000
1!
#80000
0!
#85000
1!
#90000
0!
#95000
1!
#100000
1%
0$
b10 *
0+
b11 )
b10 (
b1000000000000000000000000000000011 "
0!
b101 2
b100 1
b10 0
b100000000000000000000000000000001100000000000000000000000000000010 6
b1000000000000000000000000000000011 4
b11 /
0&
#105000
b10 .
b10 7
1!
#110000
0!
#115000
1!
#120000
0!
#125000
1!
#130000
0!
#135000
1!
#140000
0!
#145000
1!
#150000
0!
#155000
1!
#160000
0!
#165000
1!
#170000
0!
#175000
1!
#180000
0!
#185000
1!
#190000
0!
#195000
1!
#200000
0%
0'
0!
bz0 5
03
#205000
1!
#210000
0!
#215000
1!
#220000
0!
#225000
1!
#230000
0!
#235000
1!
#240000
0!
#245000
1!
#250000
0!
#255000
1!
#260000
0!
#265000
1!
#270000
0!
#275000
1!
#280000
0!
#285000
1!
#290000
0!
#295000
1!
#300000
1$
1+
b10 )
b11 (
0%
b1100000000000000000000000000000010 "
1'
0!
b11 0
b110000000000000000000000000000001000000000000000000000000000000010 6
b1100000000000000000000000000000010 4
b10 /
bz1 5
13
#305000
1!
#310000
0!
#315000
1!
#320000
0!
#325000
1!
#330000
0!
#335000
1!
#340000
0!
#345000
1!
#350000
0!
#355000
1!
#360000
0!
#365000
1!
#370000
0!
#375000
1!
#380000
0!
#385000
1!
#390000
0!
#395000
1!
#400000
0$
0'
0!
bz0 5
03
#405000
1!
#410000
0!
#415000
1!
#420000
0!
#425000
1!
#430000
0!
#435000
1!
#440000
0!
#445000
1!
#450000
0!
#455000
1!
#460000
0!
#465000
1!
#470000
0!
#475000
1!
#480000
0!
#485000
1!
#490000
0!
#495000
1!
#500000
1%
b11 *
0+
b100 )
0$
b1100000000000000000000000000000100 "
1'
0!
b10 1
b110000000000000000000000000000010000000000000000000000000000000011 6
b1100000000000000000000000000000100 4
b100 /
bz1 5
13
#505000
b11 .
b11 7
1!
#510000
0!
#515000
1!
#520000
0!
#525000
1!
#530000
0!
#535000
1!
#540000
0!
#545000
1!
#550000
0!
#555000
1!
#560000
0!
#565000
1!
#570000
0!
#575000
1!
#580000
0!
#585000
1!
#590000
0!
#595000
1!
#600000
0%
0'
0!
bz0 5
03
#605000
1!
#610000
0!
#615000
1!
#620000
0!
#625000
1!
#630000
0!
#635000
1!
#640000
0!
#645000
1!
#650000
0!
#655000
1!
#660000
0!
#665000
1!
#670000
0!
#675000
1!
#680000
0!
#685000
1!
#690000
0!
#695000
1!
#700000
1%
1'
0!
b10 2
b101 1
bz1 5
13
#705000
1!
#710000
0!
#715000
1!
#720000
0!
#725000
1!
#730000
0!
#735000
1!
#740000
0!
#745000
1!
#750000
0!
#755000
1!
#760000
0!
#765000
1!
#770000
0!
#775000
1!
#780000
0!
#785000
1!
#790000
0!
#795000
1!
#800000
0%
0'
0!
bz0 5
03
#805000
1!
#810000
0!
#815000
1!
#820000
0!
#825000
1!
#830000
0!
#835000
1!
#840000
0!
#845000
1!
#850000
0!
#855000
1!
#860000
0!
#865000
1!
#870000
0!
#875000
1!
#880000
0!
#885000
1!
#890000
0!
#895000
1!
#900000
$dumpoff
bx 8
bx 7
bx 6
bx 5
bx 4
x3
bx 2
bx 1
bx 0
bx /
bx .
x-
x,
x+
bx *
bx )
bx (
x'
x&
x%
x$
bx #
bx "
x!
$end
