dut/binary_merger.v
// binary_merger.v
// Author: Andrew Feldman, 11/10/2021
//
// Parameterized binary merger component

module binary_merger 
              #(parameter MERGER_COORD_BITS = 32)
              (
              input wire clock,
              input wire reset,
              input wire [(2*MERGER_COORD_BITS-1):0] coord_in,
              output wire [(MERGER_COORD_BITS-1):0] coord,
              input wire selected,
              output wire [1:0] fetch_next
);
    
    wire comparison;
    wire [(MERGER_COORD_BITS-1):0] coord_0;
    wire [(MERGER_COORD_BITS-1):0] coord_1;

    // Breakout separate coordinates from input net
    assign coord_0 = coord_in[(MERGER_COORD_BITS-1):0];
    assign coord_1 = coord_in[(2*MERGER_COORD_BITS-1):MERGER_COORD_BITS];

    // Merge
    assign comparison = (coord_0 < coord_1);
    assign coord = comparison ? coord_0 : coord_1;
    assign fetch_next_from_0 = comparison & selected;
    assign fetch_next_from_1 = (~comparison) & selected;

endmodule

dut/quaternary_merger.v
// quaternary_merger.v
// Author: Andrew Feldman, 11/10/2021
//
// quaternary merger component built from three interconnected binary mergers
//
//

module quaternary_merger(input wire clock,
              input wire reset,
              input wire [63:0] coord_0,
              input wire [63:0] coord_1,
              input wire [63:0] coord_2,
              input wire [63:0] coord_3,
              output wire [63:0] coord,
              input wire selected,
              output wire [3:0] fetch_next
);

    wire [127:0] l0_out;
    wire [1:0] l1_fetch_next;  
  
    binary_merger l0_m0 (
        .clock(clock),
        .reset(reset),
        .coord_0(coord_0),
        .coord_1(coord_1),
        .coord(l0_out[63:0]),
        .selected(l1_fetch_next[0]),
        .fetch_next_from_0(fetch_next[0]),
        .fetch_next_from_1(fetch_next[1])
    );    

    binary_merger l0_m1 (
        .clock(clock),
        .reset(reset),
        .coord_0(coord_2),
        .coord_1(coord_3),
        .coord(l0_out[127:64]),
        .selected(l1_fetch_next[1]),
        .fetch_next_from_0(fetch_next[2]), 
        .fetch_next_from_1(fetch_next[3])
    );

    binary_merger l1_m0 (
        .clock(clock),
        .reset(reset),
        .coord_0(l0_out[63:0]),
        .coord_1(l0_out[127:64]),
        .coord(coord),
        .selected(selected),
        .fetch_next_from_0(l1_fetch_next[0]),
        .fetch_next_from_1(l1_fetch_next[1])
    );

endmodule

testbench/tb_quaternary_merger.v
// tb_binary_merger.v
// Author: Andrew Feldman 11/9/2021
//
// Testbench for quaternary merger component

`timescale 1ns/1ps

module tb_quaternary_merger;

    reg clk;
    reg rst;
    reg [63:0] c0;
    reg [63:0] c1;
    reg [63:0] c2;
    reg [63:0] c3;
    wire [63:0] c;
    reg sel;
    wire [3:0] fn;

    quaternary_merger dut (
        .clock(clk),
        .reset(rst),
        .coord_0(c0),
        .coord_1(c1),
        .coord_2(c2),
        .coord_3(c3),
        .coord(c),
        .selected(sel),
        .fetch_next(fn[3:0])
    );    

    always begin
        #5;
        clk = !clk;
    end

    initial begin
        $dumpfile("quaternary_merger.vcd");
        $dumpvars(0,tb_quaternary_merger);
        clk=0;
        rst=0;
        sel=1;
        c0=64'd3;
        c1=64'd2;
        c2=64'd4;
        c3=64'd1;
        #100
        sel=0;
        #100
        sel=1;
        c0=64'd3;
        c1=64'd2;
        c2=64'd1;
        c3=64'd5;
        #100
        sel=0;
        #100
        sel=1;
        c0=64'd2;
        c1=64'd1;
        c2=64'd3;
        c3=64'd5;
        #100
        sel=0;
        #100
        sel=1;
        c0=64'd1;
        c1=64'd3;
        c2=64'd3;
        c3=64'd5;
        #100
        sel=0;
        #100
        $dumpoff;
        $finish;
    end

endmodule

quaternary_merger.vcd
$date
	Tue Nov  9 23:37:42 2021
$end
$version
	Icarus Verilog
$end
$timescale
	1ps
$end
$scope module tb_quaternary_merger $end
$var wire 4 ! fn [3:0] $end
$var wire 64 " c [63:0] $end
$var reg 64 # c0 [63:0] $end
$var reg 64 $ c1 [63:0] $end
$var reg 64 % c2 [63:0] $end
$var reg 64 & c3 [63:0] $end
$var reg 1 ' clk $end
$var reg 1 ( rst $end
$var reg 1 ) sel $end
$scope module dut $end
$var wire 1 ' clock $end
$var wire 64 * coord_0 [63:0] $end
$var wire 64 + coord_1 [63:0] $end
$var wire 64 , coord_2 [63:0] $end
$var wire 64 - coord_3 [63:0] $end
$var wire 1 ( reset $end
$var wire 1 ) selected $end
$var wire 2 . l1_fetch_next [1:0] $end
$var wire 128 / l0_out [127:0] $end
$var wire 4 0 fetch_next [3:0] $end
$var wire 64 1 coord [63:0] $end
$scope module l0_m0 $end
$var wire 1 ' clock $end
$var wire 64 2 coord_0 [63:0] $end
$var wire 64 3 coord_1 [63:0] $end
$var wire 1 4 fetch_next_from_0 $end
$var wire 1 5 fetch_next_from_1 $end
$var wire 1 ( reset $end
$var wire 1 6 selected $end
$var wire 64 7 coord [63:0] $end
$var wire 1 8 comparison $end
$upscope $end
$scope module l0_m1 $end
$var wire 1 ' clock $end
$var wire 64 9 coord_0 [63:0] $end
$var wire 64 : coord_1 [63:0] $end
$var wire 1 ; fetch_next_from_0 $end
$var wire 1 < fetch_next_from_1 $end
$var wire 1 ( reset $end
$var wire 1 = selected $end
$var wire 64 > coord [63:0] $end
$var wire 1 ? comparison $end
$upscope $end
$scope module l1_m0 $end
$var wire 1 ' clock $end
$var wire 64 @ coord_0 [63:0] $end
$var wire 64 A coord_1 [63:0] $end
$var wire 1 B fetch_next_from_0 $end
$var wire 1 C fetch_next_from_1 $end
$var wire 1 ( reset $end
$var wire 1 ) selected $end
$var wire 64 D coord [63:0] $end
$var wire 1 E comparison $end
$upscope $end
$upscope $end
$upscope $end
$enddefinitions $end
#0
$dumpvars
0E
b1 D
1C
0B
b1 A
b10 @
0?
b1 >
1=
1<
0;
b1 :
b100 9
08
b10 7
06
05
04
b10 3
b11 2
b1 1
b1000 0
b10000000000000000000000000000000000000000000000000000000000000010 /
b10 .
b1 -
b100 ,
b10 +
b11 *
1)
0(
0'
b1 &
b100 %
b10 $
b11 #
b1 "
b1000 !
$end
#5000
1'
#10000
0'
#15000
1'
#20000
0'
#25000
1'
#30000
0'
#35000
1'
#40000
0'
#45000
1'
#50000
0'
#55000
1'
#60000
0'
#65000
1'
#70000
0'
#75000
1'
#80000
0'
#85000
1'
#90000
0'
#95000
1'
#100000
b0 !
b0 0
0<
0=
b0 .
0C
0'
0)
#105000
1'
#110000
0'
#115000
1'
#120000
0'
#125000
1'
#130000
0'
#135000
1'
#140000
0'
#145000
1'
#150000
0'
#155000
1'
#160000
0'
#165000
1'
#170000
0'
#175000
1'
#180000
0'
#185000
1'
#190000
0'
#195000
1'
#200000
b100 !
b100 0
1;
1=
b10 .
1C
0'
1?
b101 &
b101 -
b101 :
b1 %
b1 ,
b1 9
1)
#205000
1'
#210000
0'
#215000
1'
#220000
0'
#225000
1'
#230000
0'
#235000
1'
#240000
0'
#245000
1'
#250000
0'
#255000
1'
#260000
0'
#265000
1'
#270000
0'
#275000
1'
#280000
0'
#285000
1'
#290000
0'
#295000
1'
#300000
b0 !
b0 0
0;
0=
b0 .
0C
0'
0)
#305000
1'
#310000
0'
#315000
1'
#320000
0'
#325000
1'
#330000
0'
#335000
1'
#340000
0'
#345000
1'
#350000
0'
#355000
1'
#360000
0'
#365000
1'
#370000
0'
#375000
1'
#380000
0'
#385000
1'
#390000
0'
#395000
1'
#400000
15
16
1B
b10 !
b10 0
0;
1E
b11 A
b1 @
0=
b11 >
b110000000000000000000000000000000000000000000000000000000000000001 /
b1 7
b1 .
0C
0'
b11 %
b11 ,
b11 9
b1 $
b1 +
b1 3
b10 #
b10 *
b10 2
1)
#405000
1'
#410000
0'
#415000
1'
#420000
0'
#425000
1'
#430000
0'
#435000
1'
#440000
0'
#445000
1'
#450000
0'
#455000
1'
#460000
0'
#465000
1'
#470000
0'
#475000
1'
#480000
0'
#485000
1'
#490000
0'
#495000
1'
#500000
b0 !
b0 0
05
06
b0 .
0B
0'
0)
#505000
1'
#510000
0'
#515000
1'
#520000
0'
#525000
1'
#530000
0'
#535000
1'
#540000
0'
#545000
1'
#550000
0'
#555000
1'
#560000
0'
#565000
1'
#570000
0'
#575000
1'
#580000
0'
#585000
1'
#590000
0'
#595000
1'
#600000
b1 !
b1 0
14
16
b1 .
1B
0'
18
b11 $
b11 +
b11 3
b1 #
b1 *
b1 2
1)
#605000
1'
#610000
0'
#615000
1'
#620000
0'
#625000
1'
#630000
0'
#635000
1'
#640000
0'
#645000
1'
#650000
0'
#655000
1'
#660000
0'
#665000
1'
#670000
0'
#675000
1'
#680000
0'
#685000
1'
#690000
0'
#695000
1'
#700000
b0 !
b0 0
04
06
b0 .
0B
0'
0)
#705000
1'
#710000
0'
#715000
1'
#720000
0'
#725000
1'
#730000
0'
#735000
1'
#740000
0'
#745000
1'
#750000
0'
#755000
1'
#760000
0'
#765000
1'
#770000
0'
#775000
1'
#780000
0'
#785000
1'
#790000
0'
#795000
1'
#800000
$dumpoff
xE
bx D
xC
xB
bx A
bx @
x?
bx >
x=
x<
x;
bx :
bx 9
x8
bx 7
x6
x5
x4
bx 3
bx 2
bx 1
bx 0
bx /
bx .
bx -
bx ,
bx +
bx *
x)
x(
x'
bx &
bx %
bx $
bx #
bx "
bx !
$end
